reoptimize/REsqlite3.db
reoptimize/Restriction_Dictionary.py
reoptimize/__init__.py
reoptimize/assay_DNAs.fasta
reoptimize/make_sqlite_database.py
reoptimize/reoptimize.py
reoptimize-0.1.0a2.dist-info/DESCRIPTION.rst
reoptimize-0.1.0a2.dist-info/METADATA
reoptimize-0.1.0a2.dist-info/RECORD
reoptimize-0.1.0a2.dist-info/WHEEL
reoptimize-0.1.0a2.dist-info/entry_points.txt
reoptimize-0.1.0a2.dist-info/metadata.json
reoptimize-0.1.0a2.dist-info/top_level.txt
