Metadata-Version: 2.0
Name: reoptimize
Version: 0.1.0a2
Summary: A tool to optimize reaction conditions for restriction enzyme digests of DNA
Home-page: https://github.com/mjeltsch/reoptimize
Author: Michael Jeltsch
Author-email: michael@jeltsch.org
License: GPLv3
Keywords: DNA,restriction enzymes,recombinant DNA technology
Platform: UNKNOWN
Classifier: Development Status :: 3 - Alpha
Classifier: Intended Audience :: Science/Research
Classifier: Topic :: Scientific/Engineering :: Bio-Informatics
Classifier: Topic :: Scientific/Engineering :: Medical Science Apps.
Classifier: Topic :: Scientific/Engineering :: Chemistry
Classifier: License :: OSI Approved :: GNU General Public License v3 (GPLv3)
Classifier: Programming Language :: Python :: 3
Requires-Dist: biopython
Requires-Dist: click
